doubleml/__init__.py
doubleml/_version.py
doubleml/double_ml.py
doubleml/double_ml_framework.py
doubleml/double_ml_sampling_mixins.py
doubleml/double_ml_score_mixins.py
doubleml/data/__init__.py
doubleml/data/base_data.py
doubleml/data/did_data.py
doubleml/data/panel_data.py
doubleml/data/rdd_data.py
doubleml/data/ssm_data.py
doubleml/data/tests/__init__.py
doubleml/data/tests/conftest.py
doubleml/data/tests/test_cluster_data.py
doubleml/data/tests/test_dml_data.py
doubleml/data/tests/test_panel_data.py
doubleml/data/tests/test_panel_data_exceptions.py
doubleml/data/utils/panel_data_utils.py
doubleml/data/utils/tests/test_panel_data_utils.py
doubleml/datasets/__init__.py
doubleml/datasets/fetch_401K.py
doubleml/datasets/fetch_bonus.py
doubleml/did/__init__.py
doubleml/did/did.py
doubleml/did/did_aggregation.py
doubleml/did/did_binary.py
doubleml/did/did_cs.py
doubleml/did/did_cs_binary.py
doubleml/did/did_multi.py
doubleml/did/datasets/__init__.py
doubleml/did/datasets/dgp_did_CS2021.py
doubleml/did/datasets/dgp_did_SZ2020.py
doubleml/did/datasets/dgp_did_cs_CS2021.py
doubleml/did/tests/__init__.py
doubleml/did/tests/_utils_did_cs_manual.py
doubleml/did/tests/_utils_did_manual.py
doubleml/did/tests/conftest.py
doubleml/did/tests/test_datasets.py
doubleml/did/tests/test_did.py
doubleml/did/tests/test_did_aggregation.py
doubleml/did/tests/test_did_aggregation_exceptions.py
doubleml/did/tests/test_did_aggregation_plot.py
doubleml/did/tests/test_did_aggregation_return_types.py
doubleml/did/tests/test_did_binary_control_groups.py
doubleml/did/tests/test_did_binary_exceptions.py
doubleml/did/tests/test_did_binary_external_predictions.py
doubleml/did/tests/test_did_binary_external_predictions_unbalanced.py
doubleml/did/tests/test_did_binary_placebo.py
doubleml/did/tests/test_did_binary_ps_processor.py
doubleml/did/tests/test_did_binary_stdout.py
doubleml/did/tests/test_did_binary_tune.py
doubleml/did/tests/test_did_binary_tune_ml_models.py
doubleml-0.11.2.dist-info/licenses/LICENSE
doubleml-0.11.2.dist-info/METADATA
doubleml-0.11.2.dist-info/WHEEL
doubleml-0.11.2.dist-info/top_level.txt
doubleml-0.11.2.dist-info/RECORD
