Metadata-Version: 2.4
Name: DoubleML
Version: 0.11.2
Summary: Double Machine Learning in Python
Author: Bach, P., Chernozhukov, V., Klaassen, S., Kurz, M. S., and Spindler, M.
Maintainer-email: Sven Klaassen <sven.klaassen@uni-hamburg.de>
License: BSD 3-Clause License
Project-URL: Documentation, https://docs.doubleml.org
Project-URL: Source, https://github.com/DoubleML/doubleml-for-py
Project-URL: Bug Tracker, https://github.com/DoubleML/doubleml-for-py/issues
Classifier: Programming Language :: Python :: 3
Classifier: Programming Language :: Python :: 3.10
Classifier: Programming Language :: Python :: 3.11
Classifier: Programming Language :: Python :: 3.12
Classifier: Programming Language :: Python :: 3.13
Classifier: License :: OSI Approved :: BSD License
Classifier: Operating System :: OS Independent
Requires-Python: >=3.10
License-File: LICENSE
Requires-Dist: joblib>=1.2.0
Requires-Dist: numpy>=2.0.0
Requires-Dist: pandas>=2.0.0
Requires-Dist: scipy>=1.7.0
Requires-Dist: scikit-learn>=1.6.0
Requires-Dist: statsmodels>=0.14.0
Requires-Dist: optuna>=4.6.0
Requires-Dist: matplotlib>=3.9.0
Requires-Dist: seaborn>=0.13
Requires-Dist: plotly>=5.0.0
Requires-Dist: mypy>=1.18.0
Provides-Extra: rdd
Requires-Dist: rdrobust>=1.3.0; extra == "rdd"
Provides-Extra: dev
Requires-Dist: pytest>=8.3.0; extra == "dev"
Requires-Dist: pytest-cov>=6.0.0; extra == "dev"
Requires-Dist: xgboost>=2.1.0; extra == "dev"
Requires-Dist: lightgbm>=4.6.0; extra == "dev"
Requires-Dist: black>=25.1.0; extra == "dev"
Requires-Dist: ruff>=0.11.1; extra == "dev"
Requires-Dist: pre-commit>=4.2.0; extra == "dev"
Dynamic: license-file
